flexga/__init__.py
flexga/argmeta.py
flexga/flexga.py
flexga/genome.py
flexga/population.py
flexga/utils.py
flexga-1.1.2.dist-info/LICENSE
flexga-1.1.2.dist-info/METADATA
flexga-1.1.2.dist-info/WHEEL
flexga-1.1.2.dist-info/top_level.txt
flexga-1.1.2.dist-info/RECORD
