Metadata-Version: 2.1
Name: flexga
Version: 1.1.2
Summary: A simple, multi-purpose genetic algorithm supporting both continuous and discrete design variables.
Home-page: https://github.com/epeters3/flexga
Author: Evan Peterson
Author-email: evanpeterson17@gmail.com
License: MIT
Platform: UNKNOWN
Requires-Dist: numpy (>=1.18.1)
